README.md
setup.py
elma/__init__.py
elma/constants.py
elma/error.py
elma/lgr.py
elma/models.py
elma/packing.py
elma/utils.py
elma.egg-info/PKG-INFO
elma.egg-info/SOURCES.txt
elma.egg-info/dependency_links.txt
elma.egg-info/requires.txt
elma.egg-info/top_level.txt