Metadata-Version: 1.2
Name: elma
Version: 0.8.1
Summary: Elma Python Library.
Home-page: http://github.com/sigvef/elma/
Maintainer: Sigve Sebastian Farstad
Maintainer-email: sigvefarstad@gmail.com
License: MIT
Platform: UNKNOWN
